hiphop/__init__.py
hiphop/_api.py
hiphop/typing.py
hiphop/_src/__init__.py
hiphop/_src/backward.py
hiphop/_src/base.py
hiphop/_src/functional.py
hiphop/_src/paramsdict.py
hiphop/_src/transform.py
hiphop/_src/initializers/__init__.py
hiphop/_src/initializers/helpers.py
hiphop/_src/initializers/initializer.py
hiphop/_src/layers/Activations.py
hiphop/_src/layers/Linear.py
hiphop/_src/layers/TensorOps.py
hiphop/_src/layers/__init__.py
hiphop/_src/module/__init__.py
hiphop/_src/module/base.py
hiphop/_src/module/transform.py
hiphop-0.0.1.dist-info/licenses/LICENSE
hiphop-0.0.1.dist-info/METADATA
hiphop-0.0.1.dist-info/WHEEL
hiphop-0.0.1.dist-info/top_level.txt
hiphop-0.0.1.dist-info/RECORD
